{
    "name": "seesaw",
    "version": "0.0.6",
    "description": "A MakeCode package for Adafruit Seesaw I2C protocol",
    "license": "MIT",
    "dependencies": {
        "core": "*"
    },
    "files": [
        "README.md",
        "seesaw.ts",
        "crickit.ts",
        "samd09.ts"
    ],
    "testFiles": [
        "test.ts"
    ],
    "public": true,
    "targetVersions": {
        "branch": "v1.1.21",
        "tag": "v1.1.21",
        "commits": "https://github.com/Microsoft/pxt-adafruit/commits/c62d6073cd2ab55d7f317bd6baaa58cb6cb861a3",
        "target": "1.1.21",
        "pxt": "3.16.5"
    }
}